{ "tracks":
	[
		{
			"name": "Neon Night",
			"trackNumber": "01",
			"url": "https://evandelia.com/blackbird/tracks/01%20Neon%20Night.mp3"
		},
		{
			"name": "Give",
			"trackNumber": "02",
			"url": "https://evandelia.com/blackbird/tracks/02%20Give.mp3"
		},
		{
			"name": "Moonshape",
			"trackNumber": "03",
			"url": "https://evandelia.com/blackbird/tracks/03%20Moonshape.mp3"
		},
		{
			"name": "Our Love",
			"trackNumber": "04",
			"url": "https://evandelia.com/blackbird/tracks/04%20Our%20Love.mp3"
		}
	]
}
